dj_notify/__init__.py
dj_notify/__main__.py
dj_notify/admin.py
dj_notify/apps.py
dj_notify/cli.py
dj_notify/models.py
dj_notify/notify.py
dj_notify/signals.py
dj_notify/urls.py
dj_notify/views.py
dj_notify-3.0.1.dist-info/licenses/LICENSE
dj_notify-3.0.1.dist-info/METADATA
dj_notify-3.0.1.dist-info/WHEEL
dj_notify-3.0.1.dist-info/entry_points.txt
dj_notify-3.0.1.dist-info/top_level.txt
dj_notify-3.0.1.dist-info/RECORD
