Metadata-Version: 2.4
Name: dj_notify
Version: 3.0.1
Summary: A simple notification tool.
Author-email: Asmita <shahasmita379@gmail.com>
Maintainer-email: Asmita <shahasmita379@gmail.com>
License: MIT
Project-URL: bugs, https://github.com/audreyfeldroy/dj_notify/issues
Project-URL: changelog, https://github.com/audreyfeldroy/dj_notify/blob/master/changelog.md
Project-URL: homepage, https://github.com/audreyfeldroy/dj_notify
Requires-Python: >=3.10
License-File: LICENSE
Requires-Dist: typer
Provides-Extra: test
Requires-Dist: coverage; extra == "test"
Requires-Dist: pytest; extra == "test"
Requires-Dist: ruff; extra == "test"
Requires-Dist: ty; extra == "test"
Dynamic: license-file
